cert_kube/__init__.py
cert_kube/kube.py
cert_kube-1.0.5.dist-info/DESCRIPTION.rst
cert_kube-1.0.5.dist-info/METADATA
cert_kube-1.0.5.dist-info/RECORD
cert_kube-1.0.5.dist-info/WHEEL
cert_kube-1.0.5.dist-info/entry_points.txt
cert_kube-1.0.5.dist-info/metadata.json
cert_kube-1.0.5.dist-info/top_level.txt
