Metadata-Version: 2.0
Name: cert-kube
Version: 1.0.5
Summary: Certbot plugin for Oracle Cloud Kubernetes
Home-page: UNKNOWN
Author: Dilan Tharaka
Author-email: tharakamd6@gmail.com
License: UNKNOWN
Platform: UNKNOWN
Requires-Dist: certbot
Requires-Dist: zope.interface
